
    Last modified 2021-1-31; size 418 bytes
        MD5 checksum 8c4734eca6e4bd6c50282358aa3735b5
        Compiled from "ObjectCreate.java"
public class org.sample.rumtime.ObjectCreate
        minor version: 0
        major version: 52
        flags: ACC_PUBLIC, ACC_SUPER
        Constant pool:
        #1 = Methodref          #4.#16         // java/lang/Object."<init>":()V
        #2 = Class              #17            // org/sample/rumtime/ObjectCreate
        #3 = Methodref          #2.#16         // org/sample/rumtime/ObjectCreate."<init>":()V
        #4 = Class              #18            // java/lang/Object
        #5 = Utf8               <init>
   #6 = Utf8               ()V
           #7 = Utf8               Code
           #8 = Utf8               LineNumberTable
           #9 = Utf8               LocalVariableTable
           #10 = Utf8               this
           #11 = Utf8               Lorg/sample/rumtime/ObjectCreate;
           #12 = Utf8               getObject
           #13 = Utf8               ()Lorg/sample/rumtime/ObjectCreate;
           #14 = Utf8               SourceFile
           #15 = Utf8               ObjectCreate.java
           #16 = NameAndType        #5:#6          // "<init>":()V
           #17 = Utf8               org/sample/rumtime/ObjectCreate
           #18 = Utf8               java/lang/Object
           {
public org.sample.rumtime.ObjectCreate();
        descriptor: ()V
        flags: ACC_PUBLIC
        Code:
        stack=1, locals=1, args_size=1
        0: aload_0
        1: invokespecial #1                  // Method java/lang/Object."<init>":()V
        4: return
        LineNumberTable:
        line 3: 0
        LocalVariableTable:
        Start  Length  Slot  Name   Signature
        0       5     0  this   Lorg/sample/rumtime/ObjectCreate;

public org.sample.rumtime.ObjectCreate getObject();
        descriptor: ()Lorg/sample/rumtime/ObjectCreate;
        flags: ACC_PUBLIC
        Code:
        stack=2, locals=1, args_size=1
        0: new           #2                  // class org/sample/rumtime/ObjectCreate
        3: dup
        4: invokespecial #3                  // Method "<init>":()V
        7: areturn
        LineNumberTable:
        line 6: 0
        LocalVariableTable:
        Start  Length  Slot  Name   Signature
        0       8     0  this   Lorg/sample/rumtime/ObjectCreate;
        }
